JSNMFuP/model.py
JSNMFuP/utils.py
code/model.py
JSNMFuP-0.0.3.dist-info/LICENSE
JSNMFuP-0.0.3.dist-info/METADATA
JSNMFuP-0.0.3.dist-info/WHEEL
JSNMFuP-0.0.3.dist-info/top_level.txt
JSNMFuP-0.0.3.dist-info/RECORD
