Metadata-Version: 2.1
Name: JSNMFuP
Version: 0.0.3
Summary: A unsupervised method for the integrative analysis of single-cell multi-omics data based on non-negative matrix factorization.
Home-page: https://github.com/ZB-JN/JSNMFuP
Author: Bai Zhang
Author-email: 942761959@qq.com
License: UNKNOWN
Platform: UNKNOWN
Classifier: Programming Language :: Python :: 3
Classifier: License :: OSI Approved :: MIT License
Classifier: Operating System :: OS Independent
Requires-Python: >=3.8
License-File: LICENSE
